[
   {
      "name":"Best Heroes",
      "hero-tiers":{
         "Ana":25,
         "Ashe":15,
         "Baptiste":15,
         "Bastion":25,
         "Brigitte":5,
         "Cassidy":5,
         "D.Va":15,
         "Doomfist":45,
         "Echo":35,
         "Genji":15,
         "Hanzo":25,
         "Junker Queen":5,
         "Junkrat":35,
         "Kiriko":45,
         "Lucio":45,
         "Mei":15,
         "Mercy":35,
         "Moira":25,
         "Orisa":25,
         "Pharah":5,
         "Ramattra":25,
         "Reaper":45,
         "Reinhardt":5,
         "Roadhog":35,
         "Sigma":25,
         "Sojourn":45,
         "Soldier: 76":25,
         "Sombra":5,
         "Symmetra":5,
         "Torbjörn":25,
         "Tracer":45,
         "Widowmaker":35,
         "Winston":45,
         "Wrecking Ball":15,
         "Zarya":5,
         "Zenyatta":15
      }
   },
   {
      "name":"Top 500",
      "hero-tiers":{
         "Ana":25,
         "Ashe":15,
         "Baptiste":25,
         "Bastion":5,
         "Brigitte":15,
         "Cassidy":5,
         "D.Va":35,
         "Doomfist":35,
         "Echo":15,
         "Genji":45,
         "Hanzo":5,
         "Junker Queen":15,
         "Junkrat":35,
         "Kiriko":35,
         "Lucio":25,
         "Mei":15,
         "Mercy":25,
         "Moira":5,
         "Orisa":15,
         "Pharah":25,
         "Ramattra":25,
         "Reaper":25,
         "Reinhardt":5,
         "Roadhog":35,
         "Sigma":5,
         "Sojourn":45,
         "Soldier: 76":5,
         "Sombra":35,
         "Symmetra":45,
         "Torbjörn":25,
         "Tracer":45,
         "Widowmaker":35,
         "Winston":45,
         "Wrecking Ball":35,
         "Zarya":45,
         "Zenyatta":25
      }
   }
]